LICENSE
MANIFEST.in
README.md
requirements.txt
setup.cfg
setup.py
cocaine/__init__.py
cocaine/anniversary.py
cocaine.egg-info/PKG-INFO
cocaine.egg-info/SOURCES.txt
cocaine.egg-info/dependency_links.txt
cocaine.egg-info/namespace_packages.txt
cocaine.egg-info/not-zip-safe
cocaine.egg-info/requires.txt
cocaine.egg-info/top_level.txt
cocaine/common/__init__.py
cocaine/decorators/__init__.py
cocaine/decorators/http_dec.py
cocaine/decorators/wsgi.py
cocaine/detail/__init__.py
cocaine/detail/api.py
cocaine/detail/baseservice.py
cocaine/detail/channel.py
cocaine/detail/defaults.py
cocaine/detail/headers.py
cocaine/detail/iotimer.py
cocaine/detail/locator.py
cocaine/detail/log.py
cocaine/detail/logger.py
cocaine/detail/secadaptor.py
cocaine/detail/service.py
cocaine/detail/trace.py
cocaine/detail/util.py
cocaine/exceptions/__init__.py
cocaine/futures/__init__.py
cocaine/logger/__init__.py
cocaine/services/__init__.py
cocaine/worker/__init__.py
cocaine/worker/disowntimer.py
cocaine/worker/message.py
cocaine/worker/request.py
cocaine/worker/response.py
cocaine/worker/worker.py
tests/requirements.txt